odoo/addons/purchase_order_product_recommendation_brand/README.rst
odoo/addons/purchase_order_product_recommendation_brand/__init__.py
odoo/addons/purchase_order_product_recommendation_brand/__manifest__.py
odoo/addons/purchase_order_product_recommendation_brand/i18n/es.po
odoo/addons/purchase_order_product_recommendation_brand/i18n/it.po
odoo/addons/purchase_order_product_recommendation_brand/i18n/purchase_order_product_recommendation_brand.pot
odoo/addons/purchase_order_product_recommendation_brand/readme/CONTRIBUTORS.md
odoo/addons/purchase_order_product_recommendation_brand/readme/DESCRIPTION.md
odoo/addons/purchase_order_product_recommendation_brand/readme/ROADMAP.md
odoo/addons/purchase_order_product_recommendation_brand/readme/USAGE.md
odoo/addons/purchase_order_product_recommendation_brand/static/description/icon.png
odoo/addons/purchase_order_product_recommendation_brand/static/description/index.html
odoo/addons/purchase_order_product_recommendation_brand/tests/__init__.py
odoo/addons/purchase_order_product_recommendation_brand/tests/test_recommendation.py
odoo/addons/purchase_order_product_recommendation_brand/wizards/__init__.py
odoo/addons/purchase_order_product_recommendation_brand/wizards/purchase_order_recommendation.py
odoo/addons/purchase_order_product_recommendation_brand/wizards/purchase_order_recommendation_view.xml
odoo_addon_purchase_order_product_recommendation_brand-18.0.1.0.0.4.dist-info/METADATA
odoo_addon_purchase_order_product_recommendation_brand-18.0.1.0.0.4.dist-info/WHEEL
odoo_addon_purchase_order_product_recommendation_brand-18.0.1.0.0.4.dist-info/top_level.txt
odoo_addon_purchase_order_product_recommendation_brand-18.0.1.0.0.4.dist-info/RECORD
